CHANGES.txt
CONTRIBUTORS.txt
MANIFEST.in
README.txt
setup.py
docs/HISTORY.txt
docs/INSTALL.txt
docs/LICENSE.GPL
docs/LICENSE.txt
my315ok/__init__.py
my315ok.store.egg-info/PKG-INFO
my315ok.store.egg-info/SOURCES.txt
my315ok.store.egg-info/dependency_links.txt
my315ok.store.egg-info/entry_points.txt
my315ok.store.egg-info/namespace_packages.txt
my315ok.store.egg-info/not-zip-safe
my315ok.store.egg-info/paster_plugins.txt
my315ok.store.egg-info/requires.txt
my315ok.store.egg-info/top_level.txt
my315ok/store/README.txt
my315ok/store/__init__.py
my315ok/store/config.py
my315ok/store/configure.zcml
my315ok/store/tests.py
my315ok/store/browser/__init__.py
my315ok/store/browser/barsview.pt
my315ok/store/browser/barsview_mini.pt
my315ok/store/browser/barsview_orig.pt
my315ok/store/browser/barsview_preview.pt
my315ok/store/browser/barsview_thumb.pt
my315ok/store/browser/configure.zcml
my315ok/store/browser/goods_image_view.pt
my315ok/store/browser/goods_image_view.py
my315ok/store/browser/parameters.html
my315ok/store/browser/store_simple_view.pt
my315ok/store/browser/storeview.pt
my315ok/store/browser/storeview.py
my315ok/store/browser/css/jqzoom.css
my315ok/store/browser/css/jqzoom.css.old
my315ok/store/browser/images/checkout.gif
my315ok/store/browser/images/goumai.gif
my315ok/store/browser/images/gouwuche.gif
my315ok/store/browser/images/header.gif
my315ok/store/browser/images/header.jpg
my315ok/store/browser/images/imgPlayer.gif
my315ok/store/browser/images/jiantou.gif
my315ok/store/browser/images/login.png
my315ok/store/browser/images/mainmenubg.gif
my315ok/store/browser/images/recommend.gif
my315ok/store/browser/images/sheng.gif
my315ok/store/browser/images/shoucang.gif
my315ok/store/browser/images/shoucangjia.gif
my315ok/store/browser/images/sousuo.gif
my315ok/store/browser/images/zoomloader.gif
my315ok/store/browser/js/Copy of imgPlayer.js
my315ok/store/browser/js/imgPlayer.js
my315ok/store/browser/js/jFav.js
my315ok/store/browser/js/jqzoom.pack.1.0.1.js
my315ok/store/content/__init__.py
my315ok/store/content/configure.zcml
my315ok/store/content/goods_image.py
my315ok/store/content/store.py
my315ok/store/i18n/plone-zh.po
my315ok/store/i18n/plone.pot
my315ok/store/interfaces/__init__.py
my315ok/store/interfaces/goods_image.py
my315ok/store/interfaces/store.py
my315ok/store/locales/my315ok.store.po
