Metadata-Version: 1.0
Name: my315ok.store
Version: 3.0
Summary: a online store system
Home-page: http://svn.plone.org/svn/plone/plone.example
Author: adam tang
Author-email: yuejun.tang@gmail.com
License: GPL
Keywords: ecommerce online store
Platform: UNKNOWN
Classifier: Framework :: Plone
Classifier: Intended Audience :: Developers
Classifier: License :: OSI Approved :: GNU General Public License (GPL)
